{"SAPcpmsUIURL":"https:\/\/hcpmsadmin-i844173trial.dispatcher.hanatrial.ondemand.com\/","ApplicationVersion":"3.0.300","ClientApplication":{"ClientApplicationProjectInfo":{"ProjectName":"Business One","OrganizationName":"SAP","OrganizationIdentifier":"SAP"},"cloudApplicationId":"com.buone.com","ClientApplicationURL":"https:\/\/hcpms-i844173trial.hanatrial.ondemand.com\/","ClientApplicationDestinations":[{"ClientDestinationAuthenticationType":"noAuth","ClientDestinationShouldGenerateNullablePropertiesWithOptionalType":true,"ClientDestinationId":"BusinessOne","ClientDestinationGeneratedClassPrefix":"B1Pre","ClientDestinationLocalMetadataURL":"file:\/\/\/Users\/i844173\/Documents\/22.%20HACKATHON%20Summits%202019%20Fiori%20iOS\/B1Metadata_OK.xml","ClientDestinationServiceClassName":"B1Class","ClientDestinationAdditionalGenerationParameters":""}],"ClientApplicationComplexProperties":{"AuthenticationType":{"ClientApplicationAuthenticationType":"noAuth"},"ClientFeatures":{"EnableLogUpload":false,"EnableLogging":false,"EnableRemoteNotifications":true,"DiscoveryServiceFeature":{"DiscoveryServiceEmailDomain":"trial-i844173trial.sapmobileplace.com","EnableDiscoveryService":true}},"SelectedDestinationId":"BusinessOne"}},"GenerateOfflineODataProvider":false,"SAPcpmsURL":"https:\/\/hcpms-i844173trial.hanatrial.ondemand.com\/","SAPcpmsConfigurationName":"SAP Cloud Platform Mobile Services"}